pynapl/APL.py
pynapl/APLBridgeSlave.py
pynapl/APLPyConnect.py
pynapl/Array.py
pynapl/ConversionInterface.py
pynapl/IPC.dyalog
pynapl/IPC.py
pynapl/Interrupt.py
pynapl/ObjectWrapper.py
pynapl/Py.dyalog
pynapl/PyEvaluator.py
pynapl/PyTest.dyalog
pynapl/RunDyalog.py
pynapl/Util.py
pynapl/WinDyalog.py
pynapl/WinPySlave.dyalog
pynapl/WinPySlave.dyapp
pynapl/__init__.py
pynapl_dyalog-0.1.0.post2.dist-info/LICENSE
pynapl_dyalog-0.1.0.post2.dist-info/METADATA
pynapl_dyalog-0.1.0.post2.dist-info/WHEEL
pynapl_dyalog-0.1.0.post2.dist-info/top_level.txt
pynapl_dyalog-0.1.0.post2.dist-info/RECORD
