Metadata-Version: 2.1
Name: pynapl-dyalog
Version: 0.1.0.post2
Summary: Python - Dyalog APL interface
Home-page: https://github.com/fastai/pynapl
Author: Dyalog
Author-email: support@dyalog.com
License: MIT
Keywords: apl dyalog-apl interface
Classifier: Development Status :: 3 - Alpha
Classifier: Intended Audience :: Developers
Classifier: Programming Language :: APL
Classifier: Programming Language :: Python :: 3.8
Classifier: Programming Language :: Python :: 3.9
Classifier: Programming Language :: Python :: 3.10
Classifier: Programming Language :: Python :: 3.11
Classifier: Programming Language :: Python :: 3.12
License-File: LICENSE
